Workbook

Sheet INTRODUCCIÓN
A1: La presente herramienta le permitirá obtener información de los impactos de la cadena de valor de un producto potencial para que, a partir de su análisis, pueda determinar la pertinencia de trabajar de manera colectiva en la gestión del mismo para alcanzar los objetivos de desarrollo local de su territorio. Antes de iniciar, no olvide guardar este archivo con el nombre del producto y del territorio.
A8: ¿Cuál es el producto que va a analizar? | F8: Artesanía enchapada en hoja caulinar de guadua
A10: ¿Cuál es el territorio donde se encuentra la iniciativa? | F10: CIRCASIA
A12: A continucación, continue diligenciando la información de la cadena de valor del producto en la pestaña "CADENA DE VALOR" Posteriormente, ingrese la información económica y de población del municipio donde se encuentra la iniciativa en la pestaña "INFO DE BASE" Finalmente, responda las preguntas de acuerdo a la investigación del producto en su comunidad en la pestaña "INVESTIGACIÓN". Al terminar, puede abrir la pestaña "RESUMEN CV" para ver los resultados preliminares del análisis. En la parte de abajo encontrará un cuadro donde puede generar su análisis particular sobre los resultados arrojados. También puede explorar las otras pestañas para ver la información en gráficos para mayor comprensión. No olvide actualizar los gráficos cada vez que ingrese o cambie información.

Sheet CADENA DE VALOR
A1: NOMBRE DEL PRODUCTO | D1: =INTRODUCCIÓN!F8 -> Artesanía enchapada en hoja caulinar de guadua
A3: Eslabon | B3: Actividad | C3: Tiempo | D3: Costo | E3: Sector económico | F3: Beneficiarios | G3: Caracterización de los beneficiarios | H3: Oferta potencial | J3: INSTRUCCIONES
J4: 1.En el presente cuadro se debe ingresar la información correspondiente al proceso de diseño, producción, marketing y consumo final del producto o servicio que se analizará. 2. Si quiere cambiar el nombre de los eslabones de acuerdo a unos que se adapten mejor a los procesos de su producto, puede hacerlo. 3. Identifique primero las actividades que se desarrollan para cumplir con tareas específicas y escríbalas en el orden de ocurrencia en la columna B. 4. Si conoce el tiempo aproximado de las actividades, escríbalo en la columna C, de lo contrario, puede dejarla vacía. 5. Escriba el costo de cada una de estas actividades en la columna D. En esta columna no se puede dejar vacía ninguna celda. 6. En la columna E, seleccione el sector económico con el que se relaciona la actividad. 7. Escriba el número de beneficiarios de cada actividad en la columna F. Estos corresponden a los que perciben directamente el costo de dicha actividad (operarios, empleados, productores, etc) 8. Caracterice a los beneficiarios de acuerdo al criterio que usted considere pertinente. Puede describir características como su oficio, población étnica, condición de vulnerabilidad, estrato socioeconómico, entre otros. Esta característica servirá para analizar la población beneficiaria de acuerdo a la necesidad del territorio. Escriba esta información en la columna G. 9. Describa la oferta potencial de personas o empresas que puedan realizar esta misma actividad en el territorio en la columna H. Si no conoce un dato exacto, puede escribir un dato aproximado. En esta columna es muy importante no repetir valores de personas o empresas que pueden desarrollar varias actividades, es decir, si las 50 personas que pueden desarrollar la actividad A son las mismas que pueden desarrollar la actividad B, no necesita escribir nuevamente el número.
A5: DISEÑO DE PRODUCTO | B5: •Realizar el diseño de la pieza de madera | C5: 8 horas | D5: 2500 | E5: Actividades profesionales, científicas y técnicas | F5: 1 | G5: Artesano Independiente | H5: 50
B6: •Realizar el dibujo del enchape | D6: 2500 | E6: Actividades profesionales, científicas y técnicas | F6: 1 | G6: Artesano Independiente
B7: •Establecer medidas y calidad de los materiales | D7: 1000 | E7: Actividades profesionales, científicas y técnicas | F7: 1 | G7: Artesano Independiente
B8: •Recolectar y preparar de hojas caulinares | D8: 5000 | E8: Agricultura, ganadería, caza, silvicultura y pesca | F8: 2 | G8: Guaduero | H8: 20
A10: PRODUCCIÓN | B10: •Comprar insumos necesarios | C10: 1 hora | D10: 4000 | E10: Comercio al por mayor y al por menor; reparación de vehículos automotores y motocicletas | F10: 1 | G10: Tienda de insumos | H10: 5
B11: •Elaborar de la pieza base de madera | C11: 3 horas | D11: 2000 | E11: Industrias Manufactureras | F11: 2 | G11: Artesano Independiente
B12: •Enchapar con hoja caulinar | C12: 3 horas | D12: 6000 | E12: Industrias Manufactureras | F12: 2 | G12: Artesano Independiente
B13: •Empacar | C13: 3 horas | D13: 1000 | E13: Industrias Manufactureras | F13: 1 | G13: Trabajador de tienda artesanal | H13: 100
A17: MARKETING | B17: •Ofrecer (directo a clientes), exhibir (entienda) o promocionar (en ferias) producto a clientes minoristas | C17: 6 HORAS | D17: 2500 | E17: Actividades de servicios administrativos y de apoyo | F17: 1 | G17: Trabajador de tienda artesanal
A20: CONSUMO | B20: Venta del producto en tiendas externas, ferias o tiendas propias | C20: 30 minutos | D20: =SUM(D5:D13)*0.1 -> 2400 | E20: Comercio al por mayor y al por menor; reparación de vehículos automotores y motocicletas | F20: 1 | G20: Trabajador de tienda artesanal
B21: Retroalimentar satisfacción del cliente | C21: 10 minutos | D21: =D20*0.2 -> 480 | E21: Actividades de servicios administrativos y de apoyo | F21: 1 | G21: Trabajador de tienda artesanal
B23: TOTALES | D23: =SUM(D5:D22) -> 29380 | F23: =SUM(F5:F22) -> 14 | H23: =SUM(H5:H22) -> 175

Sheet INFO DE BASE
A1: NOMBRE DEL MUNICIPIO | D1: =INTRODUCCIÓN!F10 -> CIRCASIA
B3: INFORMACIÓN ECONÓMICA | I3: INFORMACIÓN DE LA OFERTA | O3: INFORMACIÓN DE POBLACIÓN
B4: CÓD | C4: SECTORES ECONÓMICOS SEGÚN CÓDIGO CIIU | D4: VALOR ACTIVOS | E4: % Económico | F4: BENEFICIOS AL SECTOR | G4: % Beneficios | H4: IMPACTO ECONÓMICO | I4: # EMPRESAS | J4: % Empresas | K4: BENEFICIARIOS POR SECTOR | L4: % Benefiarios | M4: IMPACTO DE BENEFICIARIOS | O4: POBLACIÓN TOTAL | P4: 30655
B5: A | C5: Agricultura, ganadería, caza, silvicultura y pesca | D5: 93958203 | E5: =D5/$D$25 -> 0.0039638421 | F5: =SUMIF('CADENA DE VALOR'!$E$5:$E$21,'INFO DE BASE'!C5,'CADENA DE VALOR'!$D$5:$D$21) -> 5000 | G5: =F5/$F$25 -> 0.1701838 | H5: =E5*G5*100 -> 0.06745817 | I5: 10 | J5: =I5/$I$25 -> 0.013623978 | K5: =SUMIF('CADENA DE VALOR'!$E$5:$E$21,'INFO DE BASE'!C5,'CADENA DE VALOR'!$H$5:$H$21) -> 20 | L5: =K5/$K$25 -> 0.11428571 | M5: =J5*L5*100 -> 0.15570261 | O5: FAMILIAS EN TERRITORIO | P5: 8994
B6: B | C6: Explotación de minas y canteras | D6: 0 | E6: =D6/$D$25 -> 0 | F6: =SUMIF('CADENA DE VALOR'!$E$5:$E$21,'INFO DE BASE'!C6,'CADENA DE VALOR'!$D$5:$D$21) -> 0 | G6: =F6/$F$25 -> 0 | H6: =E6*G6*100 -> 0 | I6: 0 | J6: =I6/$I$25 -> 0 | K6: =SUMIF('CADENA DE VALOR'!$E$5:$E$21,'INFO DE BASE'!C6,'CADENA DE VALOR'!$H$5:$H$21) -> 0 | L6: =K6/$K$25 -> 0 | M6: =J6*L6*100 -> 0
B7: C | C7: Industrias Manufactureras | D7: 1430775589 | E7: =D7/$D$25 -> 0.060360546 | F7: =SUMIF('CADENA DE VALOR'!$E$5:$E$21,'INFO DE BASE'!C7,'CADENA DE VALOR'!$D$5:$D$21) -> 9000 | G7: =F7/$F$25 -> 0.30633084 | H7: =E7*G7*100 -> 1.8490297 | I7: 52 | J7: =I7/$I$25 -> 0.070844687 | K7: =SUMIF('CADENA DE VALOR'!$E$5:$E$21,'INFO DE BASE'!C7,'CADENA DE VALOR'!$H$5:$H$21) -> 100 | L7: =K7/$K$25 -> 0.57142857 | M7: =J7*L7*100 -> 4.0482678
B8: D | C8: Suministro de electricidad, gas, vapor y aire acondicionado | D8: 38400000 | E8: =D8/$D$25 -> 0.001619992 | F8: =SUMIF('CADENA DE VALOR'!$E$5:$E$21,'INFO DE BASE'!C8,'CADENA DE VALOR'!$D$5:$D$21) -> 0 | G8: =F8/$F$25 -> 0 | H8: =E8*G8*100 -> 0 | I8: 1 | J8: =I8/$I$25 -> 0.0013623978 | K8: =SUMIF('CADENA DE VALOR'!$E$5:$E$21,'INFO DE BASE'!C8,'CADENA DE VALOR'!$H$5:$H$21) -> 0 | L8: =K8/$K$25 -> 0 | M8: =J8*L8*100 -> 0 | O8: INSTRUCCIONES
B9: E | C9: Distribución de agua; evacuación y tratamiento de aguas residuales, gestión de desechos y actividades de saneamiento ambiental | D9: 9325000 | E9: =D9/$D$25 -> 0.00039339649 | F9: =SUMIF('CADENA DE VALOR'!$E$5:$E$21,'INFO DE BASE'!C9,'CADENA DE VALOR'!$D$5:$D$21) -> 0 | G9: =F9/$F$25 -> 0 | H9: =E9*G9*100 -> 0 | I9: 3 | J9: =I9/$I$25 -> 0.0040871935 | K9: =SUMIF('CADENA DE VALOR'!$E$5:$E$21,'INFO DE BASE'!C9,'CADENA DE VALOR'!$H$5:$H$21) -> 0 | L9: =K9/$K$25 -> 0 | M9: =J9*L9*100 -> 0 | O9: 1. Ingrese el nombre del municipio donde se está realizando el análisis en la celda D1. 2. Ingrese el total de la suma de los activos de las empresas que se registraron en cada sector económico el último año, desde las celdas D5 a D24. 3. Ingrese el número de empresas que se registraron en cada sector económico el último año, desde las celdas I5 a I24. 4. Ingrese la población total del municipio en la celda P4. 5. Ingrese el número de familias u hogares del municipio en la celda P5.
B10: F | C10: Construcción | D10: 4249344715 | E10: =D10/$D$25 -> 0.17926834 | F10: =SUMIF('CADENA DE VALOR'!$E$5:$E$21,'INFO DE BASE'!C10,'CADENA DE VALOR'!$D$5:$D$21) -> 0 | G10: =F10/$F$25 -> 0 | H10: =E10*G10*100 -> 0 | I10: 25 | J10: =I10/$I$25 -> 0.034059946 | K10: =SUMIF('CADENA DE VALOR'!$E$5:$E$21,'INFO DE BASE'!C10,'CADENA DE VALOR'!$H$5:$H$21) -> 0 | L10: =K10/$K$25 -> 0 | M10: =J10*L10*100 -> 0
B11: G | C11: Comercio al por mayor y al por menor; reparación de vehículos automotores y motocicletas | D11: 7602828219 | E11: =D11/$D$25 -> 0.32074273 | F11: =SUMIF('CADENA DE VALOR'!$E$5:$E$21,'INFO DE BASE'!C11,'CADENA DE VALOR'!$D$5:$D$21) -> 6400 | G11: =F11/$F$25 -> 0.21783526 | H11: =E11*G11*100 -> 6.9869076 | I11: 377 | J11: =I11/$I$25 -> 0.51362398 | K11: =SUMIF('CADENA DE VALOR'!$E$5:$E$21,'INFO DE BASE'!C11,'CADENA DE VALOR'!$H$5:$H$21) -> 5 | L11: =K11/$K$25 -> 0.028571429 | M11: =J11*L11*100 -> 1.4674971
B12: H | C12: Transporte y almacenamiento | D12: 1130479429 | E12: =D12/$D$25 -> 0.047691865 | F12: =SUMIF('CADENA DE VALOR'!$E$5:$E$21,'INFO DE BASE'!C12,'CADENA DE VALOR'!$D$5:$D$21) -> 0 | G12: =F12/$F$25 -> 0 | H12: =E12*G12*100 -> 0 | I12: 16 | J12: =I12/$I$25 -> 0.021798365 | K12: =SUMIF('CADENA DE VALOR'!$E$5:$E$21,'INFO DE BASE'!C12,'CADENA DE VALOR'!$H$5:$H$21) -> 0 | L12: =K12/$K$25 -> 0 | M12: =J12*L12*100 -> 0
B13: I | C13: Alojamiento y servicios de comida | D13: 8056090741 | E13: =D13/$D$25 -> 0.33986465 | F13: =SUMIF('CADENA DE VALOR'!$E$5:$E$21,'INFO DE BASE'!C13,'CADENA DE VALOR'!$D$5:$D$21) -> 0 | G13: =F13/$F$25 -> 0 | H13: =E13*G13*100 -> 0 | I13: 146 | J13: =I13/$I$25 -> 0.19891008 | K13: =SUMIF('CADENA DE VALOR'!$E$5:$E$21,'INFO DE BASE'!C13,'CADENA DE VALOR'!$H$5:$H$21) -> 0 | L13: =K13/$K$25 -> 0 | M13: =J13*L13*100 -> 0
B14: J | C14: Información y comunicaciones | D14: 274367440 | E14: =D14/$D$25 -> 0.011574819 | F14: =SUMIF('CADENA DE VALOR'!$E$5:$E$21,'INFO DE BASE'!C14,'CADENA DE VALOR'!$D$5:$D$21) -> 0 | G14: =F14/$F$25 -> 0 | H14: =E14*G14*100 -> 0 | I14: 10 | J14: =I14/$I$25 -> 0.013623978 | K14: =SUMIF('CADENA DE VALOR'!$E$5:$E$21,'INFO DE BASE'!C14,'CADENA DE VALOR'!$H$5:$H$21) -> 0 | L14: =K14/$K$25 -> 0 | M14: =J14*L14*100 -> 0
B15: K | C15: Actividades financieras y de seguros | D15: 26870000 | E15: =D15/$D$25 -> 0.0011335725 | F15: =SUMIF('CADENA DE VALOR'!$E$5:$E$21,'INFO DE BASE'!C15,'CADENA DE VALOR'!$D$5:$D$21) -> 0 | G15: =F15/$F$25 -> 0 | H15: =E15*G15*100 -> 0 | I15: 6 | J15: =I15/$I$25 -> 0.0081743869 | K15: =SUMIF('CADENA DE VALOR'!$E$5:$E$21,'INFO DE BASE'!C15,'CADENA DE VALOR'!$H$5:$H$21) -> 0 | L15: =K15/$K$25 -> 0 | M15: =J15*L15*100 -> 0
B16: L | C16: Actividades inmobiliarias | D16: 59179000 | E16: =D16/$D$25 -> 0.0024966017 | F16: =SUMIF('CADENA DE VALOR'!$E$5:$E$21,'INFO DE BASE'!C16,'CADENA DE VALOR'!$D$5:$D$21) -> 0 | G16: =F16/$F$25 -> 0 | H16: =E16*G16*100 -> 0 | I16: 7 | J16: =I16/$I$25 -> 0.0095367847 | K16: =SUMIF('CADENA DE VALOR'!$E$5:$E$21,'INFO DE BASE'!C16,'CADENA DE VALOR'!$H$5:$H$21) -> 0 | L16: =K16/$K$25 -> 0 | M16: =J16*L16*100 -> 0
B17: M | C17: Actividades profesionales, científicas y técnicas | D17: 477982754 | E17: =D17/$D$25 -> 0.020164798 | F17: =SUMIF('CADENA DE VALOR'!$E$5:$E$21,'INFO DE BASE'!C17,'CADENA DE VALOR'!$D$5:$D$21) -> 6000 | G17: =F17/$F$25 -> 0.20422056 | H17: =E17*G17*100 -> 0.41180662 | I17: 12 | J17: =I17/$I$25 -> 0.016348774 | K17: =SUMIF('CADENA DE VALOR'!$E$5:$E$21,'INFO DE BASE'!C17,'CADENA DE VALOR'!$H$5:$H$21) -> 50 | L17: =K17/$K$25 -> 0.28571429 | M17: =J17*L17*100 -> 0.46710782
B18: N | C18: Actividades de servicios administrativos y de apoyo | D18: 22000000 | E18: =D18/$D$25 -> 0.00092812041 | F18: =SUMIF('CADENA DE VALOR'!$E$5:$E$21,'INFO DE BASE'!C18,'CADENA DE VALOR'!$D$5:$D$21) -> 2980 | G18: =F18/$F$25 -> 0.10142954 | H18: =E18*G18*100 -> 0.009413883 | I18: 9 | J18: =I18/$I$25 -> 0.01226158 | K18: =SUMIF('CADENA DE VALOR'!$E$5:$E$21,'INFO DE BASE'!C18,'CADENA DE VALOR'!$H$5:$H$21) -> 0 | L18: =K18/$K$25 -> 0 | M18: =J18*L18*100 -> 0
B19: O | C19: Administración pública y defensa; planes de seguridad social de afiliación obligatoria | D19: 0 | E19: =D19/$D$25 -> 0 | F19: =SUMIF('CADENA DE VALOR'!$E$5:$E$21,'INFO DE BASE'!C19,'CADENA DE VALOR'!$D$5:$D$21) -> 0 | G19: =F19/$F$25 -> 0 | H19: =E19*G19*100 -> 0 | I19: 0 | J19: =I19/$I$25 -> 0 | K19: =SUMIF('CADENA DE VALOR'!$E$5:$E$21,'INFO DE BASE'!C19,'CADENA DE VALOR'!$H$5:$H$21) -> 0 | L19: =K19/$K$25 -> 0 | M19: =J19*L19*100 -> 0
B20: P | C20: Educación | D20: 3000000 | E20: =D20/$D$25 -> 0.00012656187 | F20: =SUMIF('CADENA DE VALOR'!$E$5:$E$21,'INFO DE BASE'!C20,'CADENA DE VALOR'!$D$5:$D$21) -> 0 | G20: =F20/$F$25 -> 0 | H20: =E20*G20*100 -> 0 | I20: 2 | J20: =I20/$I$25 -> 0.0027247956 | K20: =SUMIF('CADENA DE VALOR'!$E$5:$E$21,'INFO DE BASE'!C20,'CADENA DE VALOR'!$H$5:$H$21) -> 0 | L20: =K20/$K$25 -> 0 | M20: =J20*L20*100 -> 0
B21: Q | C21: Actividades de atención de la salud humana y de asistencia social | D21: 13953830 | E21: =D21/$D$25 -> 0.00058867429 | F21: =SUMIF('CADENA DE VALOR'!$E$5:$E$21,'INFO DE BASE'!C21,'CADENA DE VALOR'!$D$5:$D$21) -> 0 | G21: =F21/$F$25 -> 0 | H21: =E21*G21*100 -> 0 | I21: 2 | J21: =I21/$I$25 -> 0.0027247956 | K21: =SUMIF('CADENA DE VALOR'!$E$5:$E$21,'INFO DE BASE'!C21,'CADENA DE VALOR'!$H$5:$H$21) -> 0 | L21: =K21/$K$25 -> 0 | M21: =J21*L21*100 -> 0
... B24: T | C24: Actividades de los hogares individuales en calidad de empleadores | D24: 0 | E24: =D24/$D$25 -> 0 | F24: =SUMIF('CADENA DE VALOR'!$E$5:$E$21,'INFO DE BASE'!C24,'CADENA DE VALOR'!$D$5:$D$21) -> 0 | G24: =F24/$F$25 -> 0 | H24: =E24*G24*100 -> 0 | I24: 0 | J24: =I24/$I$25 -> 0 | K24: =SUMIF('CADENA DE VALOR'!$E$5:$E$21,'INFO DE BASE'!C24,'CADENA DE VALOR'!$H$5:$H$21) -> 0 | L24: =K24/$K$25 -> 0 | M24: =J24*L24*100 -> 0
D25: =SUM(D5:D24) -> 23703821020 | E25: =SUM(E5:E24) -> 1 | F25: =SUM(F5:F24) -> 29380 | G25: =SUM(G5:G24) -> 1 | H25: =SUM(H5:H24) -> 9.324616 | I25: =SUM(I5:I24) -> 734 | J25: =SUM(J5:J24) -> 1 | K25: =SUM(K5:K24) -> 175 | ... M25: =SUM(M5:M24) -> 6.1385753
M26: =IF(M25<2.5,"BAJO",IF(M25<5,"MEDIO",IF(M25<7.5,"ALTO","MUY ALTO"))) -> ALTO
C29: CÁLCULOS
C31: IMPACTO ECONÓMICO MUNICIPAL | D31: =H25 -> 9.324616
C32: =IF(H25<2.5,"BAJO",IF(H25<5,"MEDIO",IF(H25<7.5,"ALTO","MUY ALTO"))) -> MUY ALTO
C35: Número de Beneficiarios Directos | D35: ='CADENA DE VALOR'!F23 -> 14
C36: % de Beneficiarios Potenciales | D36: =(K25/'INFO DE BASE'!P5)*100 -> 1.9457416
C37: =IF(D36<2.5,"BAJO",IF(D36<5,"MEDIO",IF(D36<7.5,"ALTO","MUY ALTO"))) -> BAJO
C40: PROMEDIO | D40: =AVERAGE('CADENA DE VALOR'!D5:D22) -> 2670.9091
C41: DESVIACIÓN ESTANDAR | D41: =STDEV('CADENA DE VALOR'!D5:D22) -> 1710.8212
C42: DISTRIBUCIÓN DE LOS BENEFICIOS | D42: =(D40-D41)/D40 -> 0.3594611
C43: =IF(D41>D40,"BAJA",IF((0.7*D40)>D41<D40,"MEDIA",IF((0.5*D40)>D41<(0.7*D40),ALTA,"MUY ALTO"))) -> MUY ALTO

Sheet INVESTIGACIÓN
A1: ¡HABLEMOS DE NUESTRO PRODUCTO! | D1: Realiza una investigación en tu comunidad para que puedas responder las siguientes preguntas
B3: Posicionamiento del producto dentro del municipio | G3: INSTRUCCIONES
B4: A | C4: ¿El producto es conocido por la comunidad? | D4: SI | E4: =IF(D4="SI",1,IF(D4=" ",0,0)) -> 1
B5: B | C5: ¿La comunidad recomienda este producto? | D5: SI | E5: =IF(D5="SI",1,IF(D5=" ",0,0)) -> 1 | G5: 1. Responda las preguntas de cada sección respondiendo solo SI o NO. Puede elegir la respuesta de la lista. 2. Al terminar puede ir a la hoja resumen
B6: C | C6: ¿Las personas sienten que el producto representa su municipio? | D6: NO | E6: =IF(D6="SI",1,IF(D6=" ",0,0)) -> 0
B7: D | C7: ¿La comunidad habla con orgullo de este producto? | D7: NO | E7: =IF(D7="SI",1,IF(D7=" ",0,0)) -> 0
B8: RESULTADO: | D8: =IF(E8=4,"MUY ALTO",IF(E8=3,"ALTO",IF(E8=2,"MEDIO","BAJO"))) -> MEDIO | E8: =SUM(E4:E7) -> 2
B10: Potencial en el mercado
B11: E | C11: ¿Hay un mercado identificado para el producto? | D11: SI | E11: =IF(D11="SI",1,IF(D11=" ",0,0)) -> 1
B12: F | C12: ¿El producto se está vendiendo actualmente? | D12: SI | E12: =IF(D12="SI",1,IF(D12=" ",0,0)) -> 1
B13: G | C13: ¿El producto tiene una alta participación en el mercado? | D13: SI | E13: =IF(D13="SI",1,IF(D13=" ",0,0)) -> 1
B14: H | C14: ¿El producto es competitivo en el mercado identificado? | D14: SI | E14: =IF(D14="SI",1,IF(D14=" ",0,0)) -> 1
B15: RESULTADO: | D15: =IF(E15=4,"MUY ALTO",IF(E15=3,"ALTO",IF(E15=2,"MEDIO","BAJO"))) -> MUY ALTO | E15: =SUM(E11:E14) -> 4
B17: Oportunidad de Crecimiento
B18: H | C18: ¿La producción y venta del producto está regulada? | D18: SI | E18: =IF(D18="SI",1,IF(D18=" ",0,0)) -> 1
C19: ¿El grupo de productores/vendedores es formal? | D19: SI | E19: =IF(D19="SI",1,IF(D19=" ",0,0)) -> 1
B20: I | C20: ¿Hay interés de los entidades del territorio por fortalecer el producto? | D20: SI | E20: =IF(D20="SI",1,IF(D20=" ",0,0)) -> 1
B21: J | C21: ¿El grupo de productores/vendedores está organizado? | D21: NO | E21: =IF(D21="SI",1,IF(D21=" ",0,0)) -> 0
B22: RESULTADO: | D22: =IF(E22=4,"MUY ALTO",IF(E22=3,"ALTO",IF(E22=2,"MEDIO","BAJO"))) -> ALTO | E22: =SUM(E18:E21) -> 3

Sheet RESUMEN CV
A3: Analisis General de 6 consideraciones para producto OVOP
A4: MUNICIPIO: | C4: =INTRODUCCIÓN!F10 -> CIRCASIA
A5: PRODUCTO: | C5: =INTRODUCCIÓN!F8 -> Artesanía enchapada en hoja caulinar de guadua
B6: Asunto de Evaluacion | C6: RESULTADO
B7: Impacto económico municipal | C7: =IF(ISBLANK('INFO DE BASE'!C32),"Falta Información",IF('INFO DE BASE'!C32="MUY ALTO",'LISTAS DESPLEGABLES'!B7,IF('INFO DE BASE'!C32="ALTO",'LISTAS DESPLEGABLES'!B8,IF('INFO DE BASE'!C32="MEDIO",'LISTAS DESPLEGABLES'!B9,'LISTAS DESPLEGABLES'!B10)))) -> La comercialización colectiva del producto generá un impacto económico MUY ALTO en el territorio ya que su cadena de valor se relaciona de directamente con la composición sectorial el municipio. | E7: =IF(ISBLANK('INFO DE BASE'!C32)," ",IF('INFO DE BASE'!C32="MUY ALTO",4,IF('INFO DE BASE'!C32="ALTO",3,IF('INFO DE BASE'!C32="MEDIO",2,1)))) -> 4
B8: Número de beneficiarios potenciales | C8: =IF(ISBLANK('INFO DE BASE'!C37),"Falta Información",IF('INFO DE BASE'!C37="MUY ALTO",'LISTAS DESPLEGABLES'!B13,IF('INFO DE BASE'!C37="ALTO",'LISTAS DESPLEGABLES'!B14,IF('INFO DE BASE'!C37="MEDIO",'LISTAS DESPLEGABLES'!B15,'LISTAS DESPLEGABLES'!B16)))) -> La cadena de valor del producto tiene pocas posibilidad de involucrar nuevas personas del territorio. | E8: =IF(ISBLANK('INFO DE BASE'!C37)," ",IF('INFO DE BASE'!C37="MUY ALTO",4,IF('INFO DE BASE'!C37="ALTO",3,IF('INFO DE BASE'!C37="MEDIO",2,1)))) -> 1
B9: Distribución de los beneficios | C9: =IF(ISBLANK('INFO DE BASE'!C43),"Falta Información",IF('INFO DE BASE'!C43="MUY ALTO",'LISTAS DESPLEGABLES'!B19,IF('INFO DE BASE'!C43="ALTO",'LISTAS DESPLEGABLES'!B20,IF('INFO DE BASE'!C43="MEDIO",'LISTAS DESPLEGABLES'!B21,'LISTAS DESPLEGABLES'!B22)))) -> La distribución de los beneficios en la cadena de valor del producto es muy equitativa y beneficia a sus involucrados sin generar desigualdad | E9: =IF(ISBLANK('INFO DE BASE'!C43)," ",IF('INFO DE BASE'!C43="MUY ALTO",4,IF('INFO DE BASE'!C43="ALTO",3,IF('INFO DE BASE'!C43="MEDIO",2,1)))) -> 4
B10: Posicionamiento interno | C10: =IF(ISBLANK(INVESTIGACIÓN!D8),"Falta Información",IF(INVESTIGACIÓN!D8="MUY ALTO",'LISTAS DESPLEGABLES'!B25,IF(INVESTIGACIÓN!D8="ALTO",'LISTAS DESPLEGABLES'!B26,IF(INVESTIGACIÓN!D8="MEDIO",'LISTAS DESPLEGABLES'!B27,'LISTAS DESPLEGABLES'!B28)))) -> El producto está ligeramente apropiado por la comunidad pero se debe dar a conocer más para conectarlo con la identidad local. | E10: =INVESTIGACIÓN!E8 -> 2
B11: Potencial en el mercado | C11: =IF(ISBLANK(INVESTIGACIÓN!D15),"Falta Información",IF(INVESTIGACIÓN!D15="MUY ALTO",'LISTAS DESPLEGABLES'!B31,IF(INVESTIGACIÓN!D15="ALTO",'LISTAS DESPLEGABLES'!B32,IF(INVESTIGACIÓN!D15="MEDIO",'LISTAS DESPLEGABLES'!B33,'LISTAS DESPLEGABLES'!B34)))) -> El producto tiene muchas oportunidades para competir en el mercado. | E11: =INVESTIGACIÓN!E15 -> 4
B12: Oportunidad de crecimiento | C12: =IF(ISBLANK(INVESTIGACIÓN!D22),"Falta Información",IF(INVESTIGACIÓN!D22="MUY ALTO",'LISTAS DESPLEGABLES'!B37,IF(INVESTIGACIÓN!D22="ALTO",'LISTAS DESPLEGABLES'!B38,IF(INVESTIGACIÓN!D22="MEDIO",'LISTAS DESPLEGABLES'!B39,'LISTAS DESPLEGABLES'!B40)))) -> El producto tiene oportunidad de crecer en el territorio gracias a la organización de la comunidad y/o a la oferta institucional relacionada con el fortalecimiento del producto. | E12: =INVESTIGACIÓN!E22 -> 3
A14: Análisis del evaluador

Sheet LISTAS DESPLEGABLES
A1: SI
A2: NO
A5: RESPUESTAS DE RESULTADOS
A6: IMPACTO ECONOMICO
A7: MUY ALTO | B7: La comercialización colectiva del producto generá un impacto económico MUY ALTO en el territorio ya que su cadena de valor se relaciona de directamente con la composición sectorial el municipio.
A8: ALTO | B8: La comercialización colectiva del producto generá un impacto económico ALTO en el territorio ya que su cadena de valor tiene en cuenta varios de los sectores más fuertes en la economía local
A9: MEDIO | B9: La comercialización colectiva del producto tiene un impacto MEDIO en el territorio ya que su cadena de valor solo tiene en cuenta algunos de los sectores más fuertes de la economía local.
A10: BAJO | B10: La comercialización colectiva del producto tiene un impacto BAJO en el territorio ya que su cadena de valor no tiene en cuenta a los sectores más fuertes de la economía local.
A12: NÚMERO DE BENEFICIARIOS POTENCIALES
A13: MUY ALTO | B13: La cadena de valor del producto tiene una gran oportunidad de beneficiar un alto número de personas en el territorio si se gestiona de manera colectiva
A14: ALTO | B14: La cadena de valor del producto puede beneficiar más personas en el territorio se se gestiona de manera colectiva
A15: MEDIO | B15: La cadena de valor del producto tiene limitaciones para involucrar y extender sus beneficios a más personas en el territorio.
A16: BAJO | B16: La cadena de valor del producto tiene pocas posibilidad de involucrar nuevas personas del territorio.
A18: DISTRIBUCIÓN DE LOS BENEFICIOS
A19: MUY ALTO | B19: La distribución de los beneficios en la cadena de valor del producto es muy equitativa y beneficia a sus involucrados sin generar desigualdad
A20: ALTO | B20: La distribución de los beneficios en la cadena de valor del producto es es equitativa con sus involucrados.
A21: MEDIO | B21: La distribución de los beneficios de la cadena de valor del producto es ligeramente inequitativa con sus involucrados
A22: BAJO | B22: La distribución de los beneficios de la cadena de valor del producto es muy inequitativa entre sus involucrados
A24: POCISIONAMIENTO INTERNO
A25: MUY ALTO | B25: El producto está muy apropiado por la comunidad y representa el orgullo local
A26: ALTO | B26: El producto está apropiado por la comunidad y puede representar la identida local.
A27: MEDIO | B27: El producto está ligeramente apropiado por la comunidad pero se debe dar a conocer más para conectarlo con la identidad local.
A28: BAJO | B28: El producto no está apropiado por la comunidad y por lo tanto no representa aún una identidad local.
A30: POTENCIAL EN EL MERCADO
A31: MUY ALTO | B31: El producto tiene muchas oportunidades para competir en el mercado.
A32: ALTO | B32: El producto tiene puede competir en el mercado
A33: MEDIO | B33: Aún no hay claridad en el mercado para que el producto pueda entrar a competir
A34: BAJO | B34: El producto no tiene potencial para ser comercializado
A36: OPORTUNIDAD DE CRECIMIENTO
A37: MUY ALTO | B37: El producto tiene una oportunidad MUY ALTA de crecer en el territorio gracias a la organización de la comunidad y a la oferta institucional relacionada con el fortalecimiento del producto.
A38: ALTO | B38: El producto tiene oportunidad de crecer en el territorio gracias a la organización de la comunidad y/o a la oferta institucional relacionada con el fortalecimiento del producto.
A39: MEDIO | B39: La organización de la comunidad y la oferta institucional no tiene suficiente conexión con el crecimiento del producto.
A40: BAJO | B40: La falta de organización de la comunidad y la poca oferta institucional obstaculizan el crecimiento del producto.

Sheet DINÁMICAS
E1: VALOR ACTIVOS | F1: (Varios elementos)
A2: BENEFICIOS DIRECTOS POR SECTOR ECONÓMICO | E2: COMPOSICIÓN ECONÓMICA DEL MUNICIPIO
A3: Etiquetas de fila | B3: Suma de Costo | E3: Etiquetas de fila | F3: Suma de % Económico | G3: Suma de % Empresas
A4: Actividades de servicios administrativos y de apoyo | B4: 0.10142954 | E4: Actividades artísticas, de entretenimiento y recreación | F4: 0.0038632295 | G4: 0.017711172
A5: Actividades profesionales, científicas y técnicas | B5: 0.20422056 | E5: Actividades de atención de la salud humana y de asistencia social | F5: 0.00058867429 | G5: 0.0027247956
A6: Agricultura, ganadería, caza, silvicultura y pesca | B6: 0.1701838 | E6: Actividades de servicios administrativos y de apoyo | F6: 0.00092812041 | G6: 0.01226158
A7: Comercio al por mayor y al por menor; reparación de vehículos automotores y motocicletas | B7: 0.21783526 | E7: Actividades financieras y de seguros | F7: 0.0011335725 | G7: 0.0081743869
A8: Industrias Manufactureras | B8: 0.30633084 | E8: Actividades inmobiliarias | F8: 0.0024966017 | G8: 0.0095367847
A9: Total general | B9: 1 | E9: Actividades profesionales, científicas y técnicas | F9: 0.020164798 | G9: 0.016348774
E10: Agricultura, ganadería, caza, silvicultura y pesca | F10: 0.0039638421 | G10: 0.013623978
E11: Alojamiento y servicios de comida | F11: 0.33986465 | G11: 0.19891008
E12: Comercio al por mayor y al por menor; reparación de vehículos automotores y motocicletas | F12: 0.32074273 | G12: 0.51362398
E13: Construcción | F13: 0.17926834 | G13: 0.034059946
E14: Distribución de agua; evacuación y tratamiento de aguas residuales, gestión de desechos y actividades de saneamiento ambiental | F14: 0.00039339649 | G14: 0.0040871935
E15: Educación | F15: 0.00012656187 | G15: 0.0027247956
E16: Industrias Manufactureras | F16: 0.060360546 | G16: 0.070844687
E17: Información y comunicaciones | F17: 0.011574819 | G17: 0.013623978
E18: Otras actividades de servicios | F18: 0.0052182642 | G18: 0.058583106
E19: Suministro de electricidad, gas, vapor y aire acondicionado | F19: 0.001619992 | G19: 0.0013623978
E20: Transporte y almacenamiento | F20: 0.047691865 | G20: 0.021798365
E21: Total general | F21: 1 | G21: 1
A28: DISTRIBUCIÓN DE LOS BENEFICIOS Y OFERTA POTENCIAL
A29: Etiquetas de fila | B29: Suma de Costo | C29: Suma de Beneficiarios
A30: Artesano Independiente | B30: 14000 | C30: 7
A31: Guaduero | B31: 5000 | C31: 2
A32: Tienda de insumos | B32: 4000 | C32: 1
A33: Trabajador de tienda artesanal | B33: 6380 | C33: 4
A34: Total general | B34: 29380 | C34: 14
C36: =GETPIVOTDATA("Suma de Costo",$A$29)/GETPIVOTDATA("Suma de Beneficiarios",$A$29) -> 2098.5714
